{
  "tag": "2019-08-25_183304",
  "event": {
    "event_type": "touch",
    "x": null,
    "y": null,
    "view": {
      "package": "com.textra",
      "visible": true,
      "checkable": false,
      "child_count": 0,
      "editable": false,
      "clickable": true,
      "is_password": false,
      "focusable": true,
      "enabled": true,
      "content_description": null,
      "children": [],
      "focused": false,
      "bounds": [
        [
          948,
          66
        ],
        [
          1080,
          220
        ]
      ],
      "resource_id": "com.textra:id/settingsToggleButton",
      "checked": false,
      "text": null,
      "class": "android.widget.ImageView",
      "scrollable": false,
      "selected": false,
      "long_clickable": false,
      "parent": 8,
      "temp_id": 12,
      "size": "132*154",
      "signature": "[class]android.widget.ImageView[resource_id]com.textra:id/settingsToggleButton[text]None[enabled,,]",
      "view_str": "144f556550c985ba81f9a891a496c939",
      "content_free_signature": "[class]android.widget.ImageView[resource_id]com.textra:id/settingsToggleButton"
    }
  },
  "start_state": "60d12ac1dd407f8715f1b10981f93cf8",
  "stop_state": "9dcd31f96034dbdc0ba3b05d4aa44869",
  "event_str": "TouchEvent(state=60d12ac1dd407f8715f1b10981f93cf8, view=144f556550c985ba81f9a891a496c939)"
}