{
  "tag": "2019-08-24_224846",
  "event": {
    "event_type": "touch",
    "x": null,
    "y": null,
    "view": {
      "package": "org.wikipedia",
      "visible": true,
      "checkable": false,
      "child_count": 0,
      "editable": false,
      "clickable": true,
      "is_password": false,
      "focusable": true,
      "enabled": true,
      "content_description": "Search my lists and articles",
      "children": [],
      "focused": false,
      "bounds": [
        [
          816,
          77
        ],
        [
          948,
          209
        ]
      ],
      "resource_id": "org.wikipedia:id/menu_search_lists",
      "checked": false,
      "text": null,
      "class": "android.widget.TextView",
      "scrollable": false,
      "selected": false,
      "long_clickable": false,
      "parent": 92,
      "temp_id": 93,
      "size": "132*132",
      "signature": "[class]android.widget.TextView[resource_id]org.wikipedia:id/menu_search_lists[text]None[enabled,,]",
      "view_str": "4488f2daa329398deeefa46f23ba9890",
      "content_free_signature": "[class]android.widget.TextView[resource_id]org.wikipedia:id/menu_search_lists"
    }
  },
  "start_state": "eccba99ad6ddcfd509449a33f77cd72d",
  "stop_state": "613dc44601fc5eb0281051b4225faeb1",
  "event_str": "TouchEvent(state=eccba99ad6ddcfd509449a33f77cd72d, view=4488f2daa329398deeefa46f23ba9890)"
}