{
  "tag": "2019-08-24_224728",
  "event": {
    "event_type": "touch",
    "x": null,
    "y": null,
    "view": {
      "package": "org.wikipedia",
      "visible": true,
      "checkable": false,
      "child_count": 0,
      "editable": false,
      "clickable": true,
      "is_password": false,
      "focusable": true,
      "enabled": true,
      "content_description": null,
      "children": [],
      "focused": false,
      "bounds": [
        [
          610,
          106
        ],
        [
          1050,
          237
        ]
      ],
      "resource_id": "org.wikipedia:id/reading_lists_overflow_sort_by",
      "checked": false,
      "text": "Sort by\u2026",
      "class": "android.widget.TextView",
      "scrollable": false,
      "selected": false,
      "long_clickable": false,
      "parent": 5,
      "temp_id": 6,
      "size": "440*131",
      "signature": "[class]android.widget.TextView[resource_id]org.wikipedia:id/reading_lists_overflow_sort_by[text]Sort by\u2026[enabled,,]",
      "view_str": "00074ea527e61abc77aebcfe4972e862",
      "content_free_signature": "[class]android.widget.TextView[resource_id]org.wikipedia:id/reading_lists_overflow_sort_by"
    }
  },
  "start_state": "0b1e4458ca08d955d59c416fdf22f21a",
  "stop_state": "fd88db6d53879b904d5dceadce47fe7a",
  "event_str": "TouchEvent(state=0b1e4458ca08d955d59c416fdf22f21a, view=00074ea527e61abc77aebcfe4972e862)"
}