{
  "tag": "2019-08-24_222529",
  "event": {
    "event_type": "touch",
    "x": null,
    "y": null,
    "view": {
      "package": "org.wikipedia",
      "visible": true,
      "checkable": false,
      "child_count": 2,
      "editable": false,
      "clickable": true,
      "is_password": false,
      "focusable": true,
      "enabled": true,
      "content_description": null,
      "children": [
        40,
        41
      ],
      "focused": false,
      "bounds": [
        [
          0,
          1974
        ],
        [
          1080,
          2028
        ]
      ],
      "resource_id": null,
      "checked": false,
      "text": null,
      "class": "android.widget.LinearLayout",
      "scrollable": false,
      "selected": false,
      "long_clickable": false,
      "parent": 12,
      "temp_id": 39,
      "size": "1080*54",
      "signature": "[class]android.widget.LinearLayout[resource_id]None[text]None[enabled,,]",
      "view_str": "0711ecdbece5e3f32179de1963323672",
      "content_free_signature": "[class]android.widget.LinearLayout[resource_id]None"
    }
  },
  "start_state": "d4d79a15b056146cd56ef286963ccb4f",
  "stop_state": "2d870d7324be2787de7a30824025ec2d",
  "event_str": "TouchEvent(state=d4d79a15b056146cd56ef286963ccb4f, view=0711ecdbece5e3f32179de1963323672)"
}