{"views": [{"checkable": false, "selected": false, "scrollable": false, "long_clickable": false, "resource_id": "com.medisafe.android.client:id/add_measurement_button", "visible": true, "enabled": true, "clickable": true, "is_password": false, "checked": false, "content_description": null, "focused": false, "class": "android.widget.LinearLayout", "children": [20], "child_count": 1, "package": "com.medisafe.android.client", "text": null, "bounds": [[32, 416], [288, 448]], "editable": false, "focusable": false, "parent": 12, "temp_id": 19, "size": "256*32", "signature": "[class]android.widget.LinearLayout[resource_id]com.medisafe.android.client:id/add_measurement_button[text]None[enabled,,]", "view_str": "537888ef950f7642f4e5caafc9f18028", "content_free_signature": "[class]android.widget.LinearLayout[resource_id]com.medisafe.android.client:id/add_measurement_button", "library": "com.medisafe.android.base.addmed.screens.views.ActionButton"}]}