{
  "tag": "2019-08-25_183343",
  "state_str": "26e551df6e60a4ed2c209c0aab118932",
  "state_str_content_free": "1e3660b106ed01cc8581f51805a7fcd8",
  "foreground_activity": "com.textra/com.mplus.lib.ui.settings.sections.main.SettingsActivity",
  "activity_stack": [
    "com.textra/com.mplus.lib.ui.settings.sections.main.SettingsActivity",
    "com.textra/com.mplus.lib.ui.main.Main"
  ],
  "background_services": [
    "com.google.android.gms/.deviceconnection.service.DeviceConnectionWatcherService",
    "com.google.android.gms/com.google.android.location.places.service.PlaceDetectionAsyncService",
    "com.android.systemui/.keyguard.KeyguardService",
    "com.android.systemui/.ImageWallpaper",
    "com.google.android.gms/com.google.android.location.geocode.GeocodeService",
    "com.google.android.gms/.auth.setup.devicesignals.LockScreenService",
    "com.google.android.gms/.gcm.GcmService",
    "com.google.android.gms/.clearcut.debug.ClearcutDebugDumpService",
    "com.google.android.gms/.chimera.PersistentApiService",
    "com.android.phone/com.android.internal.telephony.CellularNetworkService",
    "com.google.android.gms/.chimera.PersistentBoundBrokerService",
    "com.google.android.gms/.chimera.GmsBoundBrokerService",
    "com.google.android.gms/.chimera.GmsApiService",
    "com.google.android.gms/.fido.fido2.pollux.CableAuthenticatorService",
    "com.google.android.googlequicksearchbox/com.google.android.apps.gsa.nowoverlayservice.DrawerOverlayService",
    "io.github.ylimit.droidbotapp/.DroidBotIME",
    "com.google.android.gms/com.google.android.location.fused.FusedLocationService",
    "com.google.android.gms/.gcm.nts.SchedulerService",
    "com.google.android.setupwizard/.logging.ScreenOnClock",
    "io.github.ylimit.droidbotapp/io.github.privacystreams.accessibility.PSAccessibilityService",
    "com.google.android.gms/com.google.android.location.geofencer.service.GeofenceProviderService",
    "com.google.android.gms/.thunderbird.EmergencyPersistentService",
    "com.android.systemui/.SystemUIService",
    "android/.hardware.location.GeofenceHardwareService",
    "com.android.se/.SecureElementService",
    "com.google.android.gms/.chimera.PersistentDirectBootAwareApiService",
    "com.google.android.ext.services/android.ext.services.notification.Assistant",
    "com.google.android.gms/.location.persistent.LocationPersistentService",
    "com.google.android.gms/com.google.android.location.internal.PendingIntentCallbackService",
    "com.google.android.gms/com.google.android.location.reporting.service.ReportingAndroidService",
    "com.google.android.gms/com.google.android.location.internal.server.GoogleLocationService",
    "com.google.android.gms/com.google.android.contextmanager.service.ContextManagerService",
    "com.google.android.gms/com.google.android.location.network.NetworkLocationService",
    "com.google.android.gms/com.google.android.location.internal.GoogleLocationManagerService",
    "com.android.phone/com.android.internal.telephony.dataconnection.CellularDataService",
    "com.android.server.telecom/.components.TelecomService",
    "com.google.android.googlequicksearchbox/com.google.android.voiceinteraction.GsaVoiceInteractionService",
    "com.android.smspush/.WapPushManager",
    "com.android.phone/.vvm.RemoteVvmTaskManager",
    "com.google.android.gms/.lockbox.service.LockboxBrokerService",
    "android/com.android.server.content.SyncJobService",
    "com.google.android.gms/.common.stats.GmsCoreStatsService",
    "com.google.android.gms/com.google.android.location.internal.server.HardwareArProviderService",
    "com.android.mms.service/.MmsService",
    "com.android.phone/.TelephonyDebugService",
    "com.google.android.videos/.service.pinning.TransferService",
    "com.google.android.apps.nexuslauncher/com.android.quickstep.TouchInteractionService"
  ],
  "views": [
    {
      "package": "com.textra",
      "visible": true,
      "checkable": false,
      "child_count": 1,
      "editable": false,
      "clickable": false,
      "is_password": false,
      "focusable": false,
      "enabled": true,
      "content_description": null,
      "children": [
        1
      ],
      "focused": false,
      "bounds": [
        [
          1,
          734
        ],
        [
          1079,
          1360
        ]
      ],
      "resource_id": null,
      "checked": false,
      "text": null,
      "class": "android.widget.FrameLayout",
      "scrollable": false,
      "selected": false,
      "long_clickable": false,
      "parent": -1,
      "temp_id": 0,
      "size": "1078*626",
      "signature": "[class]android.widget.FrameLayout[resource_id]None[text]None[enabled,,]",
      "view_str": "88a1d28c89f6ea31ca80e2e28230d9eb",
      "content_free_signature": "[class]android.widget.FrameLayout[resource_id]None"
    },
    {
      "package": "com.textra",
      "visible": true,
      "checkable": false,
      "child_count": 1,
      "editable": false,
      "clickable": false,
      "is_password": false,
      "focusable": false,
      "enabled": true,
      "content_description": null,
      "children": [
        2
      ],
      "focused": false,
      "bounds": [
        [
          1,
          734
        ],
        [
          1079,
          1360
        ]
      ],
      "resource_id": null,
      "checked": false,
      "text": null,
      "class": "android.widget.LinearLayout",
      "scrollable": false,
      "selected": false,
      "long_clickable": false,
      "parent": 0,
      "temp_id": 1,
      "size": "1078*626",
      "signature": "[class]android.widget.LinearLayout[resource_id]None[text]None[enabled,,]",
      "view_str": "40eabb1985ccee2279250e8125231747",
      "content_free_signature": "[class]android.widget.LinearLayout[resource_id]None"
    },
    {
      "package": "com.textra",
      "visible": true,
      "checkable": false,
      "child_count": 1,
      "editable": false,
      "clickable": false,
      "is_password": false,
      "focusable": false,
      "enabled": true,
      "content_description": null,
      "children": [
        3
      ],
      "focused": false,
      "bounds": [
        [
          1,
          734
        ],
        [
          1079,
          1360
        ]
      ],
      "resource_id": "android:id/content",
      "checked": false,
      "text": null,
      "class": "android.widget.FrameLayout",
      "scrollable": false,
      "selected": false,
      "long_clickable": false,
      "parent": 1,
      "temp_id": 2,
      "size": "1078*626",
      "signature": "[class]android.widget.FrameLayout[resource_id]android:id/content[text]None[enabled,,]",
      "view_str": "85382ed88c77cffd038d17fbfa3caceb",
      "content_free_signature": "[class]android.widget.FrameLayout[resource_id]android:id/content"
    },
    {
      "package": "com.textra",
      "visible": true,
      "checkable": false,
      "child_count": 1,
      "editable": false,
      "clickable": true,
      "is_password": false,
      "focusable": true,
      "enabled": true,
      "content_description": null,
      "children": [
        4
      ],
      "focused": false,
      "bounds": [
        [
          1,
          734
        ],
        [
          1079,
          1360
        ]
      ],
      "resource_id": "com.textra:id/common_dialog_outer",
      "checked": false,
      "text": null,
      "class": "android.widget.FrameLayout",
      "scrollable": false,
      "selected": false,
      "long_clickable": false,
      "parent": 2,
      "temp_id": 3,
      "size": "1078*626",
      "signature": "[class]android.widget.FrameLayout[resource_id]com.textra:id/common_dialog_outer[text]None[enabled,,]",
      "view_str": "bb618c95bc683c9cf078d91c0e365c18",
      "content_free_signature": "[class]android.widget.FrameLayout[resource_id]com.textra:id/common_dialog_outer"
    },
    {
      "package": "com.textra",
      "visible": true,
      "checkable": false,
      "child_count": 1,
      "editable": false,
      "clickable": true,
      "is_password": false,
      "focusable": true,
      "enabled": true,
      "content_description": null,
      "children": [
        5
      ],
      "focused": false,
      "bounds": [
        [
          1,
          734
        ],
        [
          1079,
          1360
        ]
      ],
      "resource_id": "com.textra:id/common_dialog_holder",
      "checked": false,
      "text": null,
      "class": "android.widget.FrameLayout",
      "scrollable": false,
      "selected": false,
      "long_clickable": false,
      "parent": 3,
      "temp_id": 4,
      "size": "1078*626",
      "signature": "[class]android.widget.FrameLayout[resource_id]com.textra:id/common_dialog_holder[text]None[enabled,,]",
      "view_str": "393e9bf403a44a34c1136adbeb33294a",
      "content_free_signature": "[class]android.widget.FrameLayout[resource_id]com.textra:id/common_dialog_holder"
    },
    {
      "package": "com.textra",
      "visible": true,
      "checkable": false,
      "child_count": 1,
      "editable": false,
      "clickable": false,
      "is_password": false,
      "focusable": false,
      "enabled": true,
      "content_description": null,
      "children": [
        6
      ],
      "focused": false,
      "bounds": [
        [
          56,
          789
        ],
        [
          1024,
          1305
        ]
      ],
      "resource_id": "com.textra:id/common_dialog",
      "checked": false,
      "text": null,
      "class": "android.widget.FrameLayout",
      "scrollable": false,
      "selected": false,
      "long_clickable": false,
      "parent": 4,
      "temp_id": 5,
      "size": "968*516",
      "signature": "[class]android.widget.FrameLayout[resource_id]com.textra:id/common_dialog[text]None[enabled,,]",
      "view_str": "a9218992a46d5177b0c6b7a56a73afc3",
      "content_free_signature": "[class]android.widget.FrameLayout[resource_id]com.textra:id/common_dialog"
    },
    {
      "package": "com.textra",
      "visible": true,
      "checkable": false,
      "child_count": 2,
      "editable": false,
      "clickable": false,
      "is_password": false,
      "focusable": false,
      "enabled": true,
      "content_description": null,
      "children": [
        7,
        9
      ],
      "focused": false,
      "bounds": [
        [
          84,
          797
        ],
        [
          996,
          1280
        ]
      ],
      "resource_id": null,
      "checked": false,
      "text": null,
      "class": "android.widget.LinearLayout",
      "scrollable": false,
      "selected": false,
      "long_clickable": false,
      "parent": 5,
      "temp_id": 6,
      "size": "912*483",
      "signature": "[class]android.widget.LinearLayout[resource_id]None[text]None[enabled,,]",
      "view_str": "09900e2ce5030dd5c439659a743d663f",
      "content_free_signature": "[class]android.widget.LinearLayout[resource_id]None"
    },
    {
      "package": "com.textra",
      "visible": true,
      "checkable": false,
      "child_count": 1,
      "editable": false,
      "clickable": false,
      "is_password": false,
      "focusable": false,
      "enabled": true,
      "content_description": null,
      "children": [
        8
      ],
      "focused": false,
      "bounds": [
        [
          84,
          797
        ],
        [
          996,
          959
        ]
      ],
      "resource_id": "com.textra:id/titleHolder",
      "checked": false,
      "text": null,
      "class": "android.widget.LinearLayout",
      "scrollable": false,
      "selected": false,
      "long_clickable": false,
      "parent": 6,
      "temp_id": 7,
      "size": "912*162",
      "signature": "[class]android.widget.LinearLayout[resource_id]com.textra:id/titleHolder[text]None[enabled,,]",
      "view_str": "2def7118364ce50bac00fdf14e05b80a",
      "content_free_signature": "[class]android.widget.LinearLayout[resource_id]com.textra:id/titleHolder"
    },
    {
      "package": "com.textra",
      "visible": true,
      "checkable": false,
      "child_count": 0,
      "editable": false,
      "clickable": false,
      "is_password": false,
      "focusable": false,
      "enabled": true,
      "content_description": null,
      "children": [],
      "focused": false,
      "bounds": [
        [
          128,
          841
        ],
        [
          952,
          915
        ]
      ],
      "resource_id": "com.textra:id/title",
      "checked": false,
      "text": "Enter Your Mobile Number",
      "class": "android.widget.TextView",
      "scrollable": false,
      "selected": false,
      "long_clickable": false,
      "parent": 7,
      "temp_id": 8,
      "size": "824*74",
      "signature": "[class]android.widget.TextView[resource_id]com.textra:id/title[text]Enter Your Mobile Number[enabled,,]",
      "view_str": "6084b1aa028aad2c07129bec712b091b",
      "content_free_signature": "[class]android.widget.TextView[resource_id]com.textra:id/title"
    },
    {
      "package": "com.textra",
      "visible": true,
      "checkable": false,
      "child_count": 1,
      "editable": false,
      "clickable": false,
      "is_password": false,
      "focusable": false,
      "enabled": true,
      "content_description": null,
      "children": [
        10
      ],
      "focused": false,
      "bounds": [
        [
          84,
          959
        ],
        [
          996,
          1280
        ]
      ],
      "resource_id": "com.textra:id/common_dialog_inner",
      "checked": false,
      "text": null,
      "class": "android.widget.LinearLayout",
      "scrollable": false,
      "selected": false,
      "long_clickable": false,
      "parent": 6,
      "temp_id": 9,
      "size": "912*321",
      "signature": "[class]android.widget.LinearLayout[resource_id]com.textra:id/common_dialog_inner[text]None[enabled,,]",
      "view_str": "35e33087b7b36f90b2047eac1adef3b4",
      "content_free_signature": "[class]android.widget.LinearLayout[resource_id]com.textra:id/common_dialog_inner"
    },
    {
      "package": "com.textra",
      "visible": true,
      "checkable": false,
      "child_count": 2,
      "editable": false,
      "clickable": false,
      "is_password": false,
      "focusable": false,
      "enabled": true,
      "content_description": null,
      "children": [
        11,
        12
      ],
      "focused": false,
      "bounds": [
        [
          84,
          959
        ],
        [
          996,
          1280
        ]
      ],
      "resource_id": null,
      "checked": false,
      "text": null,
      "class": "android.widget.LinearLayout",
      "scrollable": false,
      "selected": false,
      "long_clickable": false,
      "parent": 9,
      "temp_id": 10,
      "size": "912*321",
      "signature": "[class]android.widget.LinearLayout[resource_id]None[text]None[enabled,,]",
      "view_str": "6bb7df941b83ddca61187320c3e819d7",
      "content_free_signature": "[class]android.widget.LinearLayout[resource_id]None"
    },
    {
      "package": "com.textra",
      "visible": true,
      "checkable": false,
      "child_count": 0,
      "editable": true,
      "clickable": true,
      "is_password": false,
      "focusable": true,
      "enabled": true,
      "content_description": null,
      "children": [],
      "focused": true,
      "bounds": [
        [
          128,
          1003
        ],
        [
          952,
          1062
        ]
      ],
      "resource_id": "com.textra:id/text",
      "checked": false,
      "text": "(555) 521-5554",
      "class": "android.widget.EditText",
      "scrollable": false,
      "selected": false,
      "long_clickable": true,
      "parent": 10,
      "temp_id": 11,
      "size": "824*59",
      "signature": "[class]android.widget.EditText[resource_id]com.textra:id/text[text](555) 521-5554[enabled,,]",
      "view_str": "174f92eaed88e05dca9a00f41abb6218",
      "content_free_signature": "[class]android.widget.EditText[resource_id]com.textra:id/text"
    },
    {
      "package": "com.textra",
      "visible": true,
      "checkable": false,
      "child_count": 2,
      "editable": false,
      "clickable": false,
      "is_password": false,
      "focusable": false,
      "enabled": true,
      "content_description": null,
      "children": [
        13,
        14
      ],
      "focused": false,
      "bounds": [
        [
          468,
          1106
        ],
        [
          996,
          1280
        ]
      ],
      "resource_id": "com.textra:id/dialogButtonPanel",
      "checked": false,
      "text": null,
      "class": "android.widget.LinearLayout",
      "scrollable": false,
      "selected": false,
      "long_clickable": false,
      "parent": 10,
      "temp_id": 12,
      "size": "528*174",
      "signature": "[class]android.widget.LinearLayout[resource_id]com.textra:id/dialogButtonPanel[text]None[enabled,,]",
      "view_str": "8f4687045aebab5d751ffa2ea20bac51",
      "content_free_signature": "[class]android.widget.LinearLayout[resource_id]com.textra:id/dialogButtonPanel"
    },
    {
      "package": "com.textra",
      "visible": true,
      "checkable": false,
      "child_count": 0,
      "editable": false,
      "clickable": true,
      "is_password": false,
      "focusable": true,
      "enabled": true,
      "content_description": null,
      "children": [],
      "focused": false,
      "bounds": [
        [
          468,
          1136
        ],
        [
          710,
          1236
        ]
      ],
      "resource_id": "com.textra:id/cancel",
      "checked": false,
      "text": "CANCEL",
      "class": "android.widget.Button",
      "scrollable": false,
      "selected": false,
      "long_clickable": false,
      "parent": 12,
      "temp_id": 13,
      "size": "242*100",
      "signature": "[class]android.widget.Button[resource_id]com.textra:id/cancel[text]CANCEL[enabled,,]",
      "view_str": "4700015ac136d18efdf086823307c85e",
      "content_free_signature": "[class]android.widget.Button[resource_id]com.textra:id/cancel"
    },
    {
      "package": "com.textra",
      "visible": true,
      "checkable": false,
      "child_count": 0,
      "editable": false,
      "clickable": true,
      "is_password": false,
      "focusable": true,
      "enabled": true,
      "content_description": null,
      "children": [],
      "focused": false,
      "bounds": [
        [
          710,
          1136
        ],
        [
          952,
          1236
        ]
      ],
      "resource_id": "com.textra:id/ok",
      "checked": false,
      "text": "OKAY",
      "class": "android.widget.Button",
      "scrollable": false,
      "selected": false,
      "long_clickable": false,
      "parent": 12,
      "temp_id": 14,
      "size": "242*100",
      "signature": "[class]android.widget.Button[resource_id]com.textra:id/ok[text]OKAY[enabled,,]",
      "view_str": "7079e79f8f965c01b61e06223b4b5e24",
      "content_free_signature": "[class]android.widget.Button[resource_id]com.textra:id/ok"
    }
  ]
}