{"views": [{"package": "com.buzzfeed.tasty", "visible": true, "checkable": false, "child_count": 3, "editable": false, "clickable": false, "is_password": false, "focusable": true, "enabled": true, "content_description": null, "children": [7, 20, 39], "focused": false, "bounds": [[0, 24], [320, 432]], "resource_id": "com.buzzfeed.tasty:id/viewPager", "checked": false, "text": null, "class": "androidx.n.a.b", "scrollable": true, "selected": false, "long_clickable": false, "parent": 5, "temp_id": 6, "size": "320*408", "signature": "[class]androidx.n.a.b[resource_id]com.buzzfeed.tasty:id/viewPager[text]None[enabled,,]", "view_str": "640c8582aa81c887294c375b30982afc", "content_free_signature": "[class]androidx.n.a.b[resource_id]com.buzzfeed.tasty:id/viewPager", "library": "com.buzzfeed.common.ui.views.BuzzFeedViewPager"}]}