{"views": [{"checkable": false, "selected": false, "scrollable": false, "long_clickable": false, "resource_id": "ar.com.fennoma.psicotest:id/appodealBannerView", "visible": true, "enabled": true, "clickable": false, "is_password": false, "checked": false, "content_description": null, "focused": false, "class": "android.widget.FrameLayout", "children": [22], "child_count": 1, "package": "ar.com.fennoma.psicotest", "text": null, "bounds": [[0, 430], [320, 480]], "editable": false, "focusable": false, "parent": 17, "temp_id": 21, "size": "320*50", "signature": "[class]android.widget.FrameLayout[resource_id]ar.com.fennoma.psicotest:id/appodealBannerView[text]None[enabled,,]", "view_str": "24735dafc27969d1de48cba97ccad5c6", "content_free_signature": "[class]android.widget.FrameLayout[resource_id]ar.com.fennoma.psicotest:id/appodealBannerView", "library": "com.appodeal.ads.BannerView"}]}