{"views": [{"package": "com.streema.simpleradio", "visible": true, "checkable": false, "child_count": 0, "editable": false, "clickable": false, "is_password": false, "focusable": false, "enabled": true, "content_description": null, "children": [], "focused": false, "bounds": [[0, 128], [320, 480]], "resource_id": "com.streema.simpleradio:id/radio_list_view", "checked": false, "text": null, "class": "android.widget.ListView", "scrollable": false, "selected": false, "long_clickable": false, "parent": 20, "temp_id": 21, "size": "320*352", "signature": "[class]android.widget.ListView[resource_id]com.streema.simpleradio:id/radio_list_view[text]None[enabled,,]", "view_str": "62638d1afa619e7408b0367fe62d5916", "content_free_signature": "[class]android.widget.ListView[resource_id]com.streema.simpleradio:id/radio_list_view", "library": "com.mobeta.android.dslv.DragSortListView"}]}