{"views": [{"package": "com.musicstreaming.freemusic", "visible": true, "checkable": false, "child_count": 1, "editable": false, "clickable": false, "is_password": false, "focusable": false, "enabled": true, "content_description": null, "children": [13], "focused": false, "bounds": [[0, 72], [320, 480]], "resource_id": "com.musicstreaming.freemusic:id/pull_refresh_list", "checked": false, "text": null, "class": "android.widget.LinearLayout", "scrollable": false, "selected": false, "long_clickable": false, "parent": 5, "temp_id": 12, "size": "320*408", "signature": "[class]android.widget.LinearLayout[resource_id]com.musicstreaming.freemusic:id/pull_refresh_list[text]None[enabled,,]", "view_str": "b962c0bc6cb1f3bcc43446691ae5d2d9", "content_free_signature": "[class]android.widget.LinearLayout[resource_id]com.musicstreaming.freemusic:id/pull_refresh_list", "library": "com.handmark.pulltorefresh.library.PullToRefreshListView"}]}