{
  "tag": "2019-08-24_221835",
  "state_str": "25d32d2b43b3301e62d47979f5e1eed3",
  "state_str_content_free": "fe6a01820483522259d61967b53fbf44",
  "foreground_activity": "org.wikipedia/.feed.news.NewsActivity",
  "activity_stack": [
    "org.wikipedia/.feed.news.NewsActivity",
    "org.wikipedia/.main.MainActivity"
  ],
  "background_services": [
    "com.google.android.music/.dial.DialMediaRouteProviderService",
    "com.google.android.gms/.icing.service.AppIndexingService",
    "com.google.android.gms/.deviceconnection.service.DeviceConnectionWatcherService",
    "com.google.android.gms/com.google.android.location.places.service.PlaceDetectionAsyncService",
    "com.android.systemui/.keyguard.KeyguardService",
    "com.android.systemui/.ImageWallpaper",
    "com.google.android.gms/com.google.android.location.geocode.GeocodeService",
    "com.google.android.gms/.auth.setup.devicesignals.LockScreenService",
    "com.google.android.gms/.gcm.GcmService",
    "com.google.android.gms/.clearcut.debug.ClearcutDebugDumpService",
    "com.google.android.gms/.chimera.PersistentApiService",
    "com.android.phone/com.android.internal.telephony.CellularNetworkService",
    "com.google.android.gms/.chimera.PersistentBoundBrokerService",
    "com.google.android.gms/.chimera.GmsBoundBrokerService",
    "com.google.android.gms/.fido.fido2.pollux.CableAuthenticatorService",
    "com.google.android.googlequicksearchbox/com.google.android.apps.gsa.nowoverlayservice.DrawerOverlayService",
    "io.github.ylimit.droidbotapp/.DroidBotIME",
    "com.google.android.gms/com.google.android.location.fused.FusedLocationService",
    "com.google.android.gms/.gcm.nts.SchedulerService",
    "com.google.android.setupwizard/.logging.ScreenOnClock",
    "io.github.ylimit.droidbotapp/io.github.privacystreams.accessibility.PSAccessibilityService",
    "com.google.android.gms/com.google.android.location.geofencer.service.GeofenceProviderService",
    "com.google.android.gms/.thunderbird.EmergencyPersistentService",
    "com.google.android.apps.messaging/.fcm.BugleFirebaseInstanceIDService",
    "com.android.chrome/org.chromium.content.app.SandboxedProcessService1",
    "com.android.systemui/.SystemUIService",
    "com.android.chrome/org.chromium.content.app.PrivilegedProcessService0",
    "android/.hardware.location.GeofenceHardwareService",
    "com.android.se/.SecureElementService",
    "com.google.android.gms/.chimera.GmsIntentOperationService",
    "com.google.android.gms/.chimera.PersistentDirectBootAwareApiService",
    "com.google.android.ext.services/android.ext.services.notification.Assistant",
    "com.google.android.gms/.location.persistent.LocationPersistentService",
    "com.google.android.gms/com.google.android.location.internal.PendingIntentCallbackService",
    "com.google.android.gms/com.google.android.location.reporting.service.ReportingAndroidService",
    "com.google.android.gms/com.google.android.location.internal.server.GoogleLocationService",
    "com.google.android.gms/com.google.android.contextmanager.service.ContextManagerService",
    "com.google.android.gms/com.google.android.location.network.NetworkLocationService",
    "com.google.android.gms/com.google.android.location.internal.GoogleLocationManagerService",
    "com.android.phone/com.android.internal.telephony.dataconnection.CellularDataService",
    "com.android.server.telecom/.components.TelecomService",
    "com.google.android.googlequicksearchbox/com.google.android.voiceinteraction.GsaVoiceInteractionService",
    "com.android.smspush/.WapPushManager",
    "com.android.phone/.vvm.RemoteVvmTaskManager",
    "com.google.android.gms/.lockbox.service.LockboxBrokerService",
    "android/com.android.server.content.SyncJobService",
    "com.google.android.gms/.common.stats.GmsCoreStatsService",
    "com.google.android.gms/com.google.android.location.internal.server.HardwareArProviderService",
    "com.android.providers.media/.MediaScannerService",
    "com.google.android.gm/com.google.firebase.iid.FirebaseInstanceIdService",
    "com.android.phone/.TelephonyDebugService",
    "com.google.android.videos/.service.pinning.TransferService",
    "com.google.android.apps.nexuslauncher/com.android.quickstep.TouchInteractionService",
    "org.wikipedia/com.mapbox.android.telemetry.TelemetryService",
    "com.google.android.gms/.chimera.GmsIntentOperationService",
    "com.android.providers.media/.MediaScannerService"
  ],
  "views": [
    {
      "package": "org.wikipedia",
      "visible": true,
      "checkable": false,
      "child_count": 2,
      "editable": false,
      "clickable": false,
      "is_password": false,
      "focusable": false,
      "enabled": true,
      "content_description": null,
      "children": [
        1,
        30
      ],
      "focused": false,
      "bounds": [
        [
          0,
          0
        ],
        [
          1080,
          2160
        ]
      ],
      "resource_id": null,
      "checked": false,
      "text": null,
      "class": "android.widget.FrameLayout",
      "scrollable": false,
      "selected": false,
      "long_clickable": false,
      "parent": -1,
      "temp_id": 0,
      "size": "1080*2160",
      "signature": "[class]android.widget.FrameLayout[resource_id]None[text]None[enabled,,]",
      "view_str": "9f41b8bcf5aaac5bb7452f1b4d6668af",
      "content_free_signature": "[class]android.widget.FrameLayout[resource_id]None"
    },
    {
      "package": "org.wikipedia",
      "visible": true,
      "checkable": false,
      "child_count": 1,
      "editable": false,
      "clickable": false,
      "is_password": false,
      "focusable": false,
      "enabled": true,
      "content_description": null,
      "children": [
        2
      ],
      "focused": false,
      "bounds": [
        [
          0,
          0
        ],
        [
          1080,
          2028
        ]
      ],
      "resource_id": null,
      "checked": false,
      "text": null,
      "class": "android.widget.LinearLayout",
      "scrollable": false,
      "selected": false,
      "long_clickable": false,
      "parent": 0,
      "temp_id": 1,
      "size": "1080*2028",
      "signature": "[class]android.widget.LinearLayout[resource_id]None[text]None[enabled,,]",
      "view_str": "f0aaee06b1df8181f3a432567ef7c7c7",
      "content_free_signature": "[class]android.widget.LinearLayout[resource_id]None"
    },
    {
      "package": "org.wikipedia",
      "visible": true,
      "checkable": false,
      "child_count": 1,
      "editable": false,
      "clickable": false,
      "is_password": false,
      "focusable": false,
      "enabled": true,
      "content_description": null,
      "children": [
        3
      ],
      "focused": false,
      "bounds": [
        [
          0,
          0
        ],
        [
          1080,
          2028
        ]
      ],
      "resource_id": null,
      "checked": false,
      "text": null,
      "class": "android.widget.FrameLayout",
      "scrollable": false,
      "selected": false,
      "long_clickable": false,
      "parent": 1,
      "temp_id": 2,
      "size": "1080*2028",
      "signature": "[class]android.widget.FrameLayout[resource_id]None[text]None[enabled,,]",
      "view_str": "3c53f01d015950927deff2ff20953d93",
      "content_free_signature": "[class]android.widget.FrameLayout[resource_id]None"
    },
    {
      "package": "org.wikipedia",
      "visible": true,
      "checkable": false,
      "child_count": 1,
      "editable": false,
      "clickable": false,
      "is_password": false,
      "focusable": false,
      "enabled": true,
      "content_description": null,
      "children": [
        4
      ],
      "focused": false,
      "bounds": [
        [
          0,
          0
        ],
        [
          1080,
          2028
        ]
      ],
      "resource_id": "org.wikipedia:id/action_bar_root",
      "checked": false,
      "text": null,
      "class": "android.widget.FrameLayout",
      "scrollable": false,
      "selected": false,
      "long_clickable": false,
      "parent": 2,
      "temp_id": 3,
      "size": "1080*2028",
      "signature": "[class]android.widget.FrameLayout[resource_id]org.wikipedia:id/action_bar_root[text]None[enabled,,]",
      "view_str": "6809895075f5b95a5129e285c22ec021",
      "content_free_signature": "[class]android.widget.FrameLayout[resource_id]org.wikipedia:id/action_bar_root"
    },
    {
      "package": "org.wikipedia",
      "visible": true,
      "checkable": false,
      "child_count": 1,
      "editable": false,
      "clickable": false,
      "is_password": false,
      "focusable": false,
      "enabled": true,
      "content_description": null,
      "children": [
        5
      ],
      "focused": false,
      "bounds": [
        [
          0,
          0
        ],
        [
          1080,
          2028
        ]
      ],
      "resource_id": "android:id/content",
      "checked": false,
      "text": null,
      "class": "android.widget.FrameLayout",
      "scrollable": false,
      "selected": false,
      "long_clickable": false,
      "parent": 3,
      "temp_id": 4,
      "size": "1080*2028",
      "signature": "[class]android.widget.FrameLayout[resource_id]android:id/content[text]None[enabled,,]",
      "view_str": "31645383b1b530e309aceaea8cab26e6",
      "content_free_signature": "[class]android.widget.FrameLayout[resource_id]android:id/content"
    },
    {
      "package": "org.wikipedia",
      "visible": true,
      "checkable": false,
      "child_count": 1,
      "editable": false,
      "clickable": false,
      "is_password": false,
      "focusable": false,
      "enabled": true,
      "content_description": null,
      "children": [
        6
      ],
      "focused": false,
      "bounds": [
        [
          0,
          0
        ],
        [
          1080,
          2028
        ]
      ],
      "resource_id": "org.wikipedia:id/fragment_container",
      "checked": false,
      "text": null,
      "class": "android.widget.FrameLayout",
      "scrollable": false,
      "selected": false,
      "long_clickable": false,
      "parent": 4,
      "temp_id": 5,
      "size": "1080*2028",
      "signature": "[class]android.widget.FrameLayout[resource_id]org.wikipedia:id/fragment_container[text]None[enabled,,]",
      "view_str": "7534ceafbfa11c3411a67d409e95e1ff",
      "content_free_signature": "[class]android.widget.FrameLayout[resource_id]org.wikipedia:id/fragment_container"
    },
    {
      "package": "org.wikipedia",
      "visible": true,
      "checkable": false,
      "child_count": 2,
      "editable": false,
      "clickable": false,
      "is_password": false,
      "focusable": false,
      "enabled": true,
      "content_description": null,
      "children": [
        7,
        16
      ],
      "focused": false,
      "bounds": [
        [
          0,
          0
        ],
        [
          1080,
          2028
        ]
      ],
      "resource_id": null,
      "checked": false,
      "text": null,
      "class": "android.view.ViewGroup",
      "scrollable": false,
      "selected": false,
      "long_clickable": false,
      "parent": 5,
      "temp_id": 6,
      "size": "1080*2028",
      "signature": "[class]android.view.ViewGroup[resource_id]None[text]None[enabled,,]",
      "view_str": "fd534c049d233d1a4d3eb7d43a999cb4",
      "content_free_signature": "[class]android.view.ViewGroup[resource_id]None"
    },
    {
      "package": "org.wikipedia",
      "visible": true,
      "checkable": false,
      "child_count": 1,
      "editable": false,
      "clickable": false,
      "is_password": false,
      "focusable": false,
      "enabled": true,
      "content_description": null,
      "children": [
        8
      ],
      "focused": false,
      "bounds": [
        [
          0,
          0
        ],
        [
          1080,
          660
        ]
      ],
      "resource_id": "org.wikipedia:id/news_app_bar",
      "checked": false,
      "text": null,
      "class": "android.widget.LinearLayout",
      "scrollable": false,
      "selected": false,
      "long_clickable": false,
      "parent": 6,
      "temp_id": 7,
      "size": "1080*660",
      "signature": "[class]android.widget.LinearLayout[resource_id]org.wikipedia:id/news_app_bar[text]None[enabled,,]",
      "view_str": "e37db19496603d341d3bbf26259d67f8",
      "content_free_signature": "[class]android.widget.LinearLayout[resource_id]org.wikipedia:id/news_app_bar"
    },
    {
      "package": "org.wikipedia",
      "visible": true,
      "checkable": false,
      "child_count": 2,
      "editable": false,
      "clickable": false,
      "is_password": false,
      "focusable": false,
      "enabled": true,
      "content_description": "",
      "children": [
        9,
        12
      ],
      "focused": false,
      "bounds": [
        [
          0,
          0
        ],
        [
          1080,
          660
        ]
      ],
      "resource_id": "org.wikipedia:id/news_toolbar_container",
      "checked": false,
      "text": null,
      "class": "android.widget.FrameLayout",
      "scrollable": false,
      "selected": false,
      "long_clickable": false,
      "parent": 7,
      "temp_id": 8,
      "size": "1080*660",
      "signature": "[class]android.widget.FrameLayout[resource_id]org.wikipedia:id/news_toolbar_container[text]None[enabled,,]",
      "view_str": "0ed6f2f521be259609c7532b59f14e8c",
      "content_free_signature": "[class]android.widget.FrameLayout[resource_id]org.wikipedia:id/news_toolbar_container"
    },
    {
      "package": "org.wikipedia",
      "visible": true,
      "checkable": false,
      "child_count": 2,
      "editable": false,
      "clickable": false,
      "is_password": false,
      "focusable": false,
      "enabled": true,
      "content_description": null,
      "children": [
        10,
        11
      ],
      "focused": false,
      "bounds": [
        [
          0,
          0
        ],
        [
          1080,
          660
        ]
      ],
      "resource_id": null,
      "checked": false,
      "text": null,
      "class": "android.widget.FrameLayout",
      "scrollable": false,
      "selected": false,
      "long_clickable": false,
      "parent": 8,
      "temp_id": 9,
      "size": "1080*660",
      "signature": "[class]android.widget.FrameLayout[resource_id]None[text]None[enabled,,]",
      "view_str": "0ae3761c77e1f591a36ceaa9a24c33d6",
      "content_free_signature": "[class]android.widget.FrameLayout[resource_id]None"
    },
    {
      "package": "org.wikipedia",
      "visible": true,
      "checkable": false,
      "child_count": 0,
      "editable": false,
      "clickable": false,
      "is_password": false,
      "focusable": false,
      "enabled": true,
      "content_description": null,
      "children": [],
      "focused": false,
      "bounds": [
        [
          0,
          0
        ],
        [
          1080,
          660
        ]
      ],
      "resource_id": "org.wikipedia:id/view_news_fullscreen_gradient",
      "checked": false,
      "text": null,
      "class": "android.view.View",
      "scrollable": false,
      "selected": false,
      "long_clickable": false,
      "parent": 9,
      "temp_id": 10,
      "size": "1080*660",
      "signature": "[class]android.view.View[resource_id]org.wikipedia:id/view_news_fullscreen_gradient[text]None[enabled,,]",
      "view_str": "d4e3eb4363d7e35316b48959cf1e894e",
      "content_free_signature": "[class]android.view.View[resource_id]org.wikipedia:id/view_news_fullscreen_gradient"
    },
    {
      "package": "org.wikipedia",
      "visible": true,
      "checkable": false,
      "child_count": 0,
      "editable": false,
      "clickable": false,
      "is_password": false,
      "focusable": false,
      "enabled": true,
      "content_description": null,
      "children": [],
      "focused": false,
      "bounds": [
        [
          0,
          0
        ],
        [
          1080,
          660
        ]
      ],
      "resource_id": "org.wikipedia:id/view_news_fullscreen_header_image",
      "checked": false,
      "text": null,
      "class": "android.widget.ImageView",
      "scrollable": false,
      "selected": false,
      "long_clickable": false,
      "parent": 9,
      "temp_id": 11,
      "size": "1080*660",
      "signature": "[class]android.widget.ImageView[resource_id]org.wikipedia:id/view_news_fullscreen_header_image[text]None[enabled,,]",
      "view_str": "7564e1c268650b998f698d7c70c16f6a",
      "content_free_signature": "[class]android.widget.ImageView[resource_id]org.wikipedia:id/view_news_fullscreen_header_image"
    },
    {
      "package": "org.wikipedia",
      "visible": true,
      "checkable": false,
      "child_count": 3,
      "editable": false,
      "clickable": false,
      "is_password": false,
      "focusable": false,
      "enabled": true,
      "content_description": null,
      "children": [
        13,
        14,
        15
      ],
      "focused": false,
      "bounds": [
        [
          0,
          66
        ],
        [
          1080,
          220
        ]
      ],
      "resource_id": "org.wikipedia:id/view_news_fullscreen_toolbar",
      "checked": false,
      "text": null,
      "class": "android.view.ViewGroup",
      "scrollable": false,
      "selected": false,
      "long_clickable": false,
      "parent": 8,
      "temp_id": 12,
      "size": "1080*154",
      "signature": "[class]android.view.ViewGroup[resource_id]org.wikipedia:id/view_news_fullscreen_toolbar[text]None[enabled,,]",
      "view_str": "71e2184c4ceb104167a15b3366b1be29",
      "content_free_signature": "[class]android.view.ViewGroup[resource_id]org.wikipedia:id/view_news_fullscreen_toolbar"
    },
    {
      "package": "org.wikipedia",
      "visible": true,
      "checkable": false,
      "child_count": 0,
      "editable": false,
      "clickable": true,
      "is_password": false,
      "focusable": true,
      "enabled": true,
      "content_description": "Navigate up",
      "children": [],
      "focused": false,
      "bounds": [
        [
          0,
          66
        ],
        [
          154,
          220
        ]
      ],
      "resource_id": null,
      "checked": false,
      "text": null,
      "class": "android.widget.ImageButton",
      "scrollable": false,
      "selected": false,
      "long_clickable": false,
      "parent": 12,
      "temp_id": 13,
      "size": "154*154",
      "signature": "[class]android.widget.ImageButton[resource_id]None[text]None[enabled,,]",
      "view_str": "add40c42e6b13bd136b0add67626576b",
      "content_free_signature": "[class]android.widget.ImageButton[resource_id]None"
    },
    {
      "package": "org.wikipedia",
      "visible": true,
      "checkable": false,
      "child_count": 0,
      "editable": false,
      "clickable": false,
      "is_password": false,
      "focusable": false,
      "enabled": true,
      "content_description": null,
      "children": [],
      "focused": false,
      "bounds": [
        [
          198,
          66
        ],
        [
          1080,
          220
        ]
      ],
      "resource_id": null,
      "checked": false,
      "text": null,
      "class": "android.view.View",
      "scrollable": false,
      "selected": false,
      "long_clickable": false,
      "parent": 12,
      "temp_id": 14,
      "size": "882*154",
      "signature": "[class]android.view.View[resource_id]None[text]None[enabled,,]",
      "view_str": "668a348c02c723ca8763b96a3c8b2036",
      "content_free_signature": "[class]android.view.View[resource_id]None"
    },
    {
      "package": "org.wikipedia",
      "visible": false,
      "checkable": false,
      "child_count": 0,
      "editable": false,
      "clickable": false,
      "is_password": false,
      "focusable": false,
      "enabled": true,
      "content_description": null,
      "children": [],
      "focused": false,
      "bounds": [
        [
          1080,
          66
        ],
        [
          1080,
          220
        ]
      ],
      "resource_id": null,
      "checked": false,
      "text": null,
      "class": "androidx.appcompat.widget.LinearLayoutCompat",
      "scrollable": false,
      "selected": false,
      "long_clickable": false,
      "parent": 12,
      "temp_id": 15,
      "size": "0*154",
      "signature": "[class]androidx.appcompat.widget.LinearLayoutCompat[resource_id]None[text]None[enabled,,]",
      "view_str": "978c94561a4ebca74b071bbd88e2cb0b",
      "content_free_signature": "[class]androidx.appcompat.widget.LinearLayoutCompat[resource_id]None"
    },
    {
      "package": "org.wikipedia",
      "visible": true,
      "checkable": false,
      "child_count": 1,
      "editable": false,
      "clickable": false,
      "is_password": false,
      "focusable": true,
      "enabled": true,
      "content_description": null,
      "children": [
        17
      ],
      "focused": false,
      "bounds": [
        [
          0,
          660
        ],
        [
          1080,
          2028
        ]
      ],
      "resource_id": null,
      "checked": false,
      "text": null,
      "class": "android.widget.ScrollView",
      "scrollable": false,
      "selected": false,
      "long_clickable": false,
      "parent": 6,
      "temp_id": 16,
      "size": "1080*1368",
      "signature": "[class]android.widget.ScrollView[resource_id]None[text]None[enabled,,]",
      "view_str": "a143a690cab93361c19431f8e0fcc0c7",
      "content_free_signature": "[class]android.widget.ScrollView[resource_id]None"
    },
    {
      "package": "org.wikipedia",
      "visible": true,
      "checkable": false,
      "child_count": 2,
      "editable": false,
      "clickable": false,
      "is_password": false,
      "focusable": false,
      "enabled": true,
      "content_description": null,
      "children": [
        18,
        19
      ],
      "focused": false,
      "bounds": [
        [
          0,
          660
        ],
        [
          1080,
          1345
        ]
      ],
      "resource_id": null,
      "checked": false,
      "text": null,
      "class": "android.widget.LinearLayout",
      "scrollable": false,
      "selected": false,
      "long_clickable": false,
      "parent": 16,
      "temp_id": 17,
      "size": "1080*685",
      "signature": "[class]android.widget.LinearLayout[resource_id]None[text]None[enabled,,]",
      "view_str": "ab90ed56887e5af57b06c51a33fe4635",
      "content_free_signature": "[class]android.widget.LinearLayout[resource_id]None"
    },
    {
      "package": "org.wikipedia",
      "visible": true,
      "checkable": false,
      "child_count": 0,
      "editable": false,
      "clickable": true,
      "is_password": false,
      "focusable": true,
      "enabled": true,
      "content_description": null,
      "children": [],
      "focused": false,
      "bounds": [
        [
          0,
          660
        ],
        [
          1080,
          930
        ]
      ],
      "resource_id": "org.wikipedia:id/view_news_fullscreen_story_text",
      "checked": false,
      "text": "At least 80 people are killed and 160 others injured in a bombing at a wedding in Kabul, Afghanistan.",
      "class": "android.widget.TextView",
      "scrollable": false,
      "selected": false,
      "long_clickable": true,
      "parent": 17,
      "temp_id": 18,
      "size": "1080*270",
      "signature": "[class]android.widget.TextView[resource_id]org.wikipedia:id/view_news_fullscreen_story_text[text]None[enabled,,]",
      "view_str": "473ee26cb323256e19329784aac605a4",
      "content_free_signature": "[class]android.widget.TextView[resource_id]org.wikipedia:id/view_news_fullscreen_story_text"
    },
    {
      "package": "org.wikipedia",
      "visible": true,
      "checkable": false,
      "child_count": 2,
      "editable": false,
      "clickable": false,
      "is_password": false,
      "focusable": true,
      "enabled": true,
      "content_description": null,
      "children": [
        20,
        25
      ],
      "focused": false,
      "bounds": [
        [
          0,
          930
        ],
        [
          1080,
          1345
        ]
      ],
      "resource_id": "org.wikipedia:id/view_news_fullscreen_link_card_list",
      "checked": false,
      "text": null,
      "class": "androidx.recyclerview.widget.RecyclerView",
      "scrollable": false,
      "selected": false,
      "long_clickable": false,
      "parent": 17,
      "temp_id": 19,
      "size": "1080*415",
      "signature": "[class]androidx.recyclerview.widget.RecyclerView[resource_id]org.wikipedia:id/view_news_fullscreen_link_card_list[text]None[enabled,,]",
      "view_str": "2635edb3d9265090079fbaf73bd11a9d",
      "content_free_signature": "[class]androidx.recyclerview.widget.RecyclerView[resource_id]org.wikipedia:id/view_news_fullscreen_link_card_list"
    },
    {
      "package": "org.wikipedia",
      "visible": true,
      "checkable": false,
      "child_count": 4,
      "editable": false,
      "clickable": true,
      "is_password": false,
      "focusable": true,
      "enabled": true,
      "content_description": null,
      "children": [
        21,
        22,
        23,
        24
      ],
      "focused": false,
      "bounds": [
        [
          0,
          931
        ],
        [
          1080,
          1137
        ]
      ],
      "resource_id": null,
      "checked": false,
      "text": null,
      "class": "android.view.ViewGroup",
      "scrollable": false,
      "selected": false,
      "long_clickable": false,
      "parent": 19,
      "temp_id": 20,
      "size": "1080*206",
      "signature": "[class]android.view.ViewGroup[resource_id]None[text]None[enabled,,]",
      "view_str": "4b97ef58043bd984a28fe8066f681560",
      "content_free_signature": "[class]android.view.ViewGroup[resource_id]None"
    },
    {
      "package": "org.wikipedia",
      "visible": true,
      "checkable": false,
      "child_count": 0,
      "editable": false,
      "clickable": false,
      "is_password": false,
      "focusable": false,
      "enabled": true,
      "content_description": null,
      "children": [],
      "focused": false,
      "bounds": [
        [
          44,
          975
        ],
        [
          154,
          1085
        ]
      ],
      "resource_id": "org.wikipedia:id/view_list_card_item_image",
      "checked": false,
      "text": null,
      "class": "android.widget.ImageView",
      "scrollable": false,
      "selected": false,
      "long_clickable": false,
      "parent": 20,
      "temp_id": 21,
      "size": "110*110",
      "signature": "[class]android.widget.ImageView[resource_id]org.wikipedia:id/view_list_card_item_image[text]None[enabled,,]",
      "view_str": "9823f20ce5d7d9b0de885cbdcce53663",
      "content_free_signature": "[class]android.widget.ImageView[resource_id]org.wikipedia:id/view_list_card_item_image"
    },
    {
      "package": "org.wikipedia",
      "visible": true,
      "checkable": false,
      "child_count": 0,
      "editable": false,
      "clickable": false,
      "is_password": false,
      "focusable": false,
      "enabled": true,
      "content_description": null,
      "children": [],
      "focused": false,
      "bounds": [
        [
          198,
          975
        ],
        [
          948,
          1034
        ]
      ],
      "resource_id": "org.wikipedia:id/view_list_card_item_title",
      "checked": false,
      "text": "17 August 2019 Kabul bombing",
      "class": "android.widget.TextView",
      "scrollable": false,
      "selected": false,
      "long_clickable": false,
      "parent": 20,
      "temp_id": 22,
      "size": "750*59",
      "signature": "[class]android.widget.TextView[resource_id]org.wikipedia:id/view_list_card_item_title[text]17 August 2019 Kabul bombing[enabled,,]",
      "view_str": "0f2cbd665cb982a32ef1f2f51c7b3fd7",
      "content_free_signature": "[class]android.widget.TextView[resource_id]org.wikipedia:id/view_list_card_item_title"
    },
    {
      "package": "org.wikipedia",
      "visible": true,
      "checkable": false,
      "child_count": 0,
      "editable": false,
      "clickable": false,
      "is_password": false,
      "focusable": false,
      "enabled": true,
      "content_description": null,
      "children": [],
      "focused": false,
      "bounds": [
        [
          198,
          1040
        ],
        [
          948,
          1093
        ]
      ],
      "resource_id": "org.wikipedia:id/view_list_card_item_subtitle",
      "checked": false,
      "text": "Suicide bombing at a wedding in Kabul",
      "class": "android.widget.TextView",
      "scrollable": false,
      "selected": false,
      "long_clickable": false,
      "parent": 20,
      "temp_id": 23,
      "size": "750*53",
      "signature": "[class]android.widget.TextView[resource_id]org.wikipedia:id/view_list_card_item_subtitle[text]Suicide bombing at a wedding in Kabul[enabled,,]",
      "view_str": "198ab58d215e7743f5f3d0e303dbaa97",
      "content_free_signature": "[class]android.widget.TextView[resource_id]org.wikipedia:id/view_list_card_item_subtitle"
    },
    {
      "package": "org.wikipedia",
      "visible": true,
      "checkable": false,
      "child_count": 0,
      "editable": false,
      "clickable": true,
      "is_password": false,
      "focusable": true,
      "enabled": true,
      "content_description": "More options",
      "children": [],
      "focused": false,
      "bounds": [
        [
          992,
          975
        ],
        [
          1058,
          1041
        ]
      ],
      "resource_id": "org.wikipedia:id/view_list_card_item_menu",
      "checked": false,
      "text": null,
      "class": "android.widget.ImageView",
      "scrollable": false,
      "selected": false,
      "long_clickable": false,
      "parent": 20,
      "temp_id": 24,
      "size": "66*66",
      "signature": "[class]android.widget.ImageView[resource_id]org.wikipedia:id/view_list_card_item_menu[text]None[enabled,,]",
      "view_str": "6ff5bd7f3a0d8ce4f6e826404f200dc2",
      "content_free_signature": "[class]android.widget.ImageView[resource_id]org.wikipedia:id/view_list_card_item_menu"
    },
    {
      "package": "org.wikipedia",
      "visible": true,
      "checkable": false,
      "child_count": 4,
      "editable": false,
      "clickable": true,
      "is_password": false,
      "focusable": true,
      "enabled": true,
      "content_description": null,
      "children": [
        26,
        27,
        28,
        29
      ],
      "focused": false,
      "bounds": [
        [
          0,
          1138
        ],
        [
          1080,
          1344
        ]
      ],
      "resource_id": null,
      "checked": false,
      "text": null,
      "class": "android.view.ViewGroup",
      "scrollable": false,
      "selected": false,
      "long_clickable": false,
      "parent": 19,
      "temp_id": 25,
      "size": "1080*206",
      "signature": "[class]android.view.ViewGroup[resource_id]None[text]None[enabled,,]",
      "view_str": "b742f592d4d7541ad29bddd794d63d7e",
      "content_free_signature": "[class]android.view.ViewGroup[resource_id]None"
    },
    {
      "package": "org.wikipedia",
      "visible": true,
      "checkable": false,
      "child_count": 0,
      "editable": false,
      "clickable": false,
      "is_password": false,
      "focusable": false,
      "enabled": true,
      "content_description": null,
      "children": [],
      "focused": false,
      "bounds": [
        [
          44,
          1182
        ],
        [
          154,
          1292
        ]
      ],
      "resource_id": "org.wikipedia:id/view_list_card_item_image",
      "checked": false,
      "text": null,
      "class": "android.widget.ImageView",
      "scrollable": false,
      "selected": false,
      "long_clickable": false,
      "parent": 25,
      "temp_id": 26,
      "size": "110*110",
      "signature": "[class]android.widget.ImageView[resource_id]org.wikipedia:id/view_list_card_item_image[text]None[enabled,,]",
      "view_str": "9823f20ce5d7d9b0de885cbdcce53663",
      "content_free_signature": "[class]android.widget.ImageView[resource_id]org.wikipedia:id/view_list_card_item_image"
    },
    {
      "package": "org.wikipedia",
      "visible": true,
      "checkable": false,
      "child_count": 0,
      "editable": false,
      "clickable": false,
      "is_password": false,
      "focusable": false,
      "enabled": true,
      "content_description": null,
      "children": [],
      "focused": false,
      "bounds": [
        [
          198,
          1182
        ],
        [
          948,
          1241
        ]
      ],
      "resource_id": "org.wikipedia:id/view_list_card_item_title",
      "checked": false,
      "text": "Kabul",
      "class": "android.widget.TextView",
      "scrollable": false,
      "selected": false,
      "long_clickable": false,
      "parent": 25,
      "temp_id": 27,
      "size": "750*59",
      "signature": "[class]android.widget.TextView[resource_id]org.wikipedia:id/view_list_card_item_title[text]Kabul[enabled,,]",
      "view_str": "3bc72127aed11816ec789b43b8bba436",
      "content_free_signature": "[class]android.widget.TextView[resource_id]org.wikipedia:id/view_list_card_item_title"
    },
    {
      "package": "org.wikipedia",
      "visible": true,
      "checkable": false,
      "child_count": 0,
      "editable": false,
      "clickable": false,
      "is_password": false,
      "focusable": false,
      "enabled": true,
      "content_description": null,
      "children": [],
      "focused": false,
      "bounds": [
        [
          198,
          1247
        ],
        [
          948,
          1300
        ]
      ],
      "resource_id": "org.wikipedia:id/view_list_card_item_subtitle",
      "checked": false,
      "text": "Metropolis and municipality in Afghanistan",
      "class": "android.widget.TextView",
      "scrollable": false,
      "selected": false,
      "long_clickable": false,
      "parent": 25,
      "temp_id": 28,
      "size": "750*53",
      "signature": "[class]android.widget.TextView[resource_id]org.wikipedia:id/view_list_card_item_subtitle[text]Metropolis and municipality in Afghanistan[enabled,,]",
      "view_str": "bb4e498fa14960e93eac1e631cf9e144",
      "content_free_signature": "[class]android.widget.TextView[resource_id]org.wikipedia:id/view_list_card_item_subtitle"
    },
    {
      "package": "org.wikipedia",
      "visible": true,
      "checkable": false,
      "child_count": 0,
      "editable": false,
      "clickable": true,
      "is_password": false,
      "focusable": true,
      "enabled": true,
      "content_description": "More options",
      "children": [],
      "focused": false,
      "bounds": [
        [
          992,
          1182
        ],
        [
          1058,
          1248
        ]
      ],
      "resource_id": "org.wikipedia:id/view_list_card_item_menu",
      "checked": false,
      "text": null,
      "class": "android.widget.ImageView",
      "scrollable": false,
      "selected": false,
      "long_clickable": false,
      "parent": 25,
      "temp_id": 29,
      "size": "66*66",
      "signature": "[class]android.widget.ImageView[resource_id]org.wikipedia:id/view_list_card_item_menu[text]None[enabled,,]",
      "view_str": "6ff5bd7f3a0d8ce4f6e826404f200dc2",
      "content_free_signature": "[class]android.widget.ImageView[resource_id]org.wikipedia:id/view_list_card_item_menu"
    },
    {
      "package": "org.wikipedia",
      "visible": false,
      "checkable": false,
      "child_count": 0,
      "editable": false,
      "clickable": false,
      "is_password": false,
      "focusable": false,
      "enabled": true,
      "content_description": null,
      "children": [],
      "focused": false,
      "bounds": [
        [
          0,
          2028
        ],
        [
          1080,
          2160
        ]
      ],
      "resource_id": "android:id/navigationBarBackground",
      "checked": false,
      "text": null,
      "class": "android.view.View",
      "scrollable": false,
      "selected": false,
      "long_clickable": false,
      "parent": 0,
      "temp_id": 30,
      "size": "1080*132",
      "signature": "[class]android.view.View[resource_id]android:id/navigationBarBackground[text]None[enabled,,]",
      "view_str": "a76ea50432748fb956e5a24974930919",
      "content_free_signature": "[class]android.view.View[resource_id]android:id/navigationBarBackground"
    }
  ]
}